pybuff/__init__.py
pybuff/grabber.py
pybuff/player.py
pybuff-0.1.4.dist-info/LICENSE
pybuff-0.1.4.dist-info/METADATA
pybuff-0.1.4.dist-info/WHEEL
pybuff-0.1.4.dist-info/top_level.txt
pybuff-0.1.4.dist-info/zip-safe
pybuff-0.1.4.dist-info/RECORD
