Metadata-Version: 2.1
Name: pybuff
Version: 0.1.4
Summary: A scraper for grabbing info from Overbuff.
Home-page: https://github.com/BigHeadGeorge/overbuff.py
Author: BigHeadGeorge
License: UNKNOWN
Platform: UNKNOWN
Classifier: Development Status :: 2 - Pre-Alpha
Classifier: License :: OSI Approved :: MIT License
Classifier: Programming Language :: Python :: 3
Classifier: Operating System :: OS Independent
Classifier: Intended Audience :: Developers
Classifier: Natural Language :: English
Classifier: Topic :: Internet
Classifier: Topic :: Software Development :: Libraries
Classifier: Topic :: Software Development :: Libraries :: Python Modules
